sciv/__init__.py
sciv/file/__init__.py
sciv/file/_read_.py
sciv/file/_write_.py
sciv/model/__init__.py
sciv/model/_core_.py
sciv/plot/__init__.py
sciv/plot/_bar_.py
sciv/plot/_barcode_.py
sciv/plot/_box_.py
sciv/plot/_bubble_.py
sciv/plot/_core_.py
sciv/plot/_graph_.py
sciv/plot/_heat_map_.py
sciv/plot/_kde_.py
sciv/plot/_line_.py
sciv/plot/_pie_.py
sciv/plot/_radar_.py
sciv/plot/_scatter_.py
sciv/plot/_venn_.py
sciv/plot/_violin_.py
sciv/preprocessing/__init__.py
sciv/preprocessing/_anndata_.py
sciv/preprocessing/_gencode_.py
sciv/preprocessing/_gsea_.py
sciv/preprocessing/_scanpy_.py
sciv/preprocessing/_scvi_.py
sciv/preprocessing/_snapatac_.py
sciv/tool/__init__.py
sciv/tool/_algorithm_.py
sciv/tool/_matrix_.py
sciv/tool/_random_walk_.py
sciv/util/__init__.py
sciv/util/_constant_.py
sciv/util/_core_.py
sciv-0.0.104.dist-info/METADATA
sciv-0.0.104.dist-info/WHEEL
sciv-0.0.104.dist-info/licenses/LICENSE
sciv-0.0.104.dist-info/RECORD
