Metadata-Version: 2.4
Name: sciv
Version: 0.0.104
Summary: Unveiling the pivotal cell types involved in variant function regulation at a single-cell resolution
Project-URL: github, https://github.com/YuZhengM/sciv
Author-email: Zheng-Min Yu <yuzmbio@163.com>
License: Copyright (c) 2024 Zheng-Min Yu
License-File: LICENSE
Keywords: Causal variant,Fine-mapping,SCIV,Single-cell epiomics,Trait,scATAC-seq
Classifier: License :: OSI Approved :: MIT License
Classifier: Operating System :: OS Independent
Classifier: Programming Language :: Python :: 3
Requires-Python: >=3.10
Requires-Dist: anndata==0.11.0
Requires-Dist: colormap==1.0.4
Requires-Dist: easydev==0.13.2
Requires-Dist: fa2-modified==0.4
Requires-Dist: forceatlas2-python==1.1
Requires-Dist: gseapy==1.1.9
Requires-Dist: h5py==3.7.0
Requires-Dist: harmonypy==0.0.10
Requires-Dist: leidenalg==0.10.2
Requires-Dist: louvain==0.8.2
Requires-Dist: magic-impute==3.0.0
Requires-Dist: matplotlib-venn==1.1.2
Requires-Dist: matplotlib==3.7.5
Requires-Dist: mudata==0.3.2
Requires-Dist: networkx==3.3
Requires-Dist: numba==0.60.0
Requires-Dist: numpy==1.26.4
Requires-Dist: palettable==3.3.3
Requires-Dist: pandas==1.5.3
Requires-Dist: psutil==7.2.1
Requires-Dist: pycomplexheatmap==1.6.1
Requires-Dist: pynndescent==0.5.13
Requires-Dist: scanpy==1.11.5
Requires-Dist: scikit-learn==1.5.2
Requires-Dist: scipy==1.11.4
Requires-Dist: scvi-tools==1.3.3
Requires-Dist: seaborn==0.13.2
Requires-Dist: statannotations==0.7.2
Requires-Dist: yzm-file==0.0.2
Requires-Dist: yzm-log==0.0.2
